Anirisuto/__init__.py
Anirisuto/async_client.py
Anirisuto/sync_client.py
Anirisuto/parsers/__init__.py
Anirisuto/parsers/parse_anime.py
Anirisuto/parsers/parse_character.py
Anirisuto/parsers/parse_manga.py
Anirisuto/queries/__init__.py
Anirisuto/queries/query.py
Anirisuto/queries/get/__init__.py
Anirisuto/queries/get/anime.graphql
Anirisuto/queries/get/character.graphql
Anirisuto/queries/get/manga.graphql
Anirisuto/queries/srch/__init__.py
Anirisuto/queries/srch/anime.graphql
Anirisuto/queries/srch/character.graphql
Anirisuto/queries/srch/manga.graphql
Anirisuto-1.0.1.dist-info/LICENSE
Anirisuto-1.0.1.dist-info/METADATA
Anirisuto-1.0.1.dist-info/WHEEL
Anirisuto-1.0.1.dist-info/top_level.txt
Anirisuto-1.0.1.dist-info/RECORD
