Metadata-Version: 2.1
Name: Anirisuto
Version: 1.0.1
Summary: A wrapper for anilist.
Home-page: https://github.com/Drum3X/Anirisuto
Author: Drum3X
Author-email: doramuekusu@gmail.com
License: Apache
Classifier: Framework :: AsyncIO
Classifier: Programming Language :: Python :: 3
Requires-Python: >=3.10
License-File: LICENSE
Requires-Dist: requests
Requires-Dist: aiohttp
